bridgecord.cp38-win_amd64.pyd
discord.dll
discord_game_sdk.dll
bridgecord-0.4.0.dist-info/LICENSE
bridgecord-0.4.0.dist-info/METADATA
bridgecord-0.4.0.dist-info/WHEEL
bridgecord-0.4.0.dist-info/top_level.txt
bridgecord-0.4.0.dist-info/RECORD
